{
  "AnonymizedUserWorkerID": "a2d15359-e691-350e-8034-7685cce53920",
  "AnonymizedWizardWorkerID": "62eeec70-6c47-578d-fd46-fef2b9b6d543",
  "BatchID": "woz_1589820124",
  "CompletionLevel": "Complete",
  "DialogueID": 2136,
  "Events": [
    {
      "Action": "instruct",
      "Agent": "UserGuide",
      "Text": "In this dialogue, either act confused, like a person with memory problems, or act concerned about the effects of the medicine.  [instruction 1 of 3]",
      "UnixTime": 1589835694
    },
    {
      "Action": "utter",
      "Agent": "User",
      "Text": "My name is Alexis and I saw Dr Johnson the other day and am not sure what he told me about the medicine.",
      "UnixTime": 1589835721
    },
    {
      "Action": "instruct",
      "Agent": "UserGuide",
      "Text": "Oh, Dr. Johnson was actually your previous doctor. Your new doctor is Dr. Morgan now. That's the one you had the appointment with. [instruction 2 of 3]",
      "UnixTime": 1589835721
    },
    {
      "APIName": "followup_doctor_appointment",
      "Action": "query",
      "Agent": "Wizard",
      "Constraints": [
        {
          "Name": "api.is_equal_to(\"Dr. Johnson\")"
        },
        {
          "PatientName": "\"Alexis\""
        }
      ],
      "UnixTime": 1589835728
    },
    {
      "APIName": "followup_doctor_appointment",
      "Action": "return_item",
      "Agent": "KnowledgeBase",
      "Item": {
        "APIName": "followup_doctor_appointment",
        "Message": "You must take your medicine 2 times a day before meals."
      },
      "TotalItems": -1
    },
    {
      "Action": "request_suggestions",
      "Agent": "Wizard",
      "PrimaryItem": {
        "APIName": "followup_doctor_appointment",
        "Message": "You must take your medicine 2 times a day before meals."
      },
      "Text": "You must take your medicine",
      "UnixTime": 1589835735
    },
    {
      "Action": "pick_suggestion",
      "ActionLabel": "doctor_inform_doctors_instructions",
      "ActionLabelOptions": [
        "doctor_inform_doctors_instructions",
        "anything_else",
        "ask_name"
      ],
      "Agent": "Wizard",
      "PrimaryItem": {
        "APIName": "followup_doctor_appointment",
        "Message": "You must take your medicine 2 times a day before meals."
      },
      "Text": "Your instructions are: You must take your medicine 2 times a day before meals..",
      "UnixTime": 1589835737
    },
    {
      "Action": "utter",
      "Agent": "User",
      "Text": "OK, I got confused about that, I also forgot it was Dr Morgan, I used to see Dr Johnson and said his name out of habit. Thanks for your help. ",
      "UnixTime": 1589835779
    },
    {
      "Action": "instruct",
      "Agent": "UserGuide",
      "Text": "Say something random about your doctors, your condition, or about something (imagined) that happened to you today. Then bring the conversation to a natural close. [instruction 3 of 3]",
      "UnixTime": 1589835779
    },
    {
      "APIName": "followup_doctor_appointment",
      "Action": "query",
      "Agent": "Wizard",
      "Constraints": [
        {
          "Name": "\"Dr. Morgan\""
        },
        {
          "PatientName": "\"Alexis\""
        }
      ],
      "PrimaryItem": {
        "APIName": "followup_doctor_appointment",
        "Message": "You must take your medicine 2 times a day before meals."
      },
      "UnixTime": 1589835784
    },
    {
      "APIName": "followup_doctor_appointment",
      "Action": "return_item",
      "Agent": "KnowledgeBase",
      "Item": {
        "APIName": "followup_doctor_appointment",
        "Message": "Take your medicine before you go to sleep. If you experience nausea, please contact your doctor immediately."
      },
      "TotalItems": -1
    },
    {
      "Action": "request_suggestions",
      "Agent": "Wizard",
      "PrimaryItem": {
        "APIName": "followup_doctor_appointment",
        "Message": "Take your medicine before you go to sleep. If you experience nausea, please contact your doctor immediately."
      },
      "Text": "Take your medicine before",
      "UnixTime": 1589835791
    },
    {
      "Action": "pick_suggestion",
      "ActionLabel": "doctor_inform_doctors_instructions",
      "ActionLabelOptions": [
        "doctor_inform_doctors_instructions",
        "hello",
        "anything_else"
      ],
      "Agent": "Wizard",
      "PrimaryItem": {
        "APIName": "followup_doctor_appointment",
        "Message": "Take your medicine before you go to sleep. If you experience nausea, please contact your doctor immediately."
      },
      "Text": "Your instructions are: Take your medicine before you go to sleep. If you experience nausea, please contact your doctor immediately..",
      "UnixTime": 1589835793
    },
    {
      "Action": "utter",
      "Agent": "User",
      "Text": "Thank you, I have been so confused since I got sick and then I had to work today too! Thanks for your help, that is all for today.",
      "UnixTime": 1589835841
    },
    {
      "Action": "request_suggestions",
      "Agent": "Wizard",
      "PrimaryItem": {
        "APIName": "followup_doctor_appointment",
        "Message": "Take your medicine before you go to sleep. If you experience nausea, please contact your doctor immediately."
      },
      "Text": "goodbye",
      "UnixTime": 1589835848
    },
    {
      "Action": "pick_suggestion",
      "ActionLabel": "doctor_bye",
      "ActionLabelOptions": [
        "doctor_bye",
        "anything_else",
        "ask_name"
      ],
      "Agent": "Wizard",
      "PrimaryItem": {
        "APIName": "followup_doctor_appointment",
        "Message": "Take your medicine before you go to sleep. If you experience nausea, please contact your doctor immediately."
      },
      "Text": "Thank you and goodbye.",
      "UnixTime": 1589835850
    },
    {
      "Action": "complete",
      "Agent": "User",
      "UnixTime": 1589835852
    }
  ],
  "FORMAT-VERSION": 7,
  "Scenario": {
    "Domains": [
      "doctor"
    ],
    "Happy": false,
    "MultiTask": false,
    "UserTask": "You (Alexis) had an appointment with Dr. Johnson the other day. Unfortunately, you forgot to write down the instructions the doctor gave you. Please followup and find out how often to take your medicine.",
    "WizardCapabilities": [
      {
        "Domain": "doctor",
        "SchemaImage": "followup_doctor_appointment.jpg",
        "Task": "followup_doctor_appointment"
      }
    ],
    "WizardTask": "Inform the user of his/her doctor's orders."
  },
  "UserQuestionnaire": [
    {
      "Answer": true,
      "Question": "Did the assistant stay calm and helpful throughout the dialogue?"
    }
  ],
  "WizardQuestionnaire": [
    {
      "Answer": true,
      "Question": "Did the user change his/her mind about what he/she wants at any time?"
    },
    {
      "Answer": false,
      "Question": "Did the user become aggressive or annoyed during the dialogue? (Note: some users may be instructed to be annoying.)"
    },
    {
      "Answer": false,
      "Question": "Where you unsure about what to do at any time? (Feel free to send us an email with details.)"
    }
  ]
}