{
  "AnonymizedUserWorkerID": "66c768ec-c1a7-affc-8806-fa55a561e851",
  "AnonymizedWizardWorkerID": "c06538fc-4352-5d92-9ced-53d9fa54e376",
  "BatchID": "woz_1589554725",
  "CompletionLevel": "Complete",
  "DialogueID": 4242,
  "Events": [
    {
      "Action": "instruct",
      "Agent": "UserGuide",
      "Text": "Explain the general situation to the robot and ask some question. [instruction 1 of 3]",
      "UnixTime": 1589566010
    },
    {
      "Action": "utter",
      "Agent": "User",
      "Text": "The life support on my spaceship is failing",
      "UnixTime": 1589566033
    },
    {
      "Action": "instruct",
      "Agent": "UserGuide",
      "Text": "Make lots of typos [instruction 2 of 3]",
      "UnixTime": 1589566033
    },
    {
      "Action": "request_suggestions",
      "Agent": "Wizard",
      "Text": "Please provide me with the Manufacturer",
      "UnixTime": 1589566047
    },
    {
      "Action": "pick_suggestion",
      "ActionLabel": "spaceship_ask_lock_manufacturer",
      "ActionLabelOptions": [
        "spaceship_ask_lock_manufacturer",
        "spaceship_ask_colour_top_cable",
        "out_of_scope"
      ],
      "Agent": "Wizard",
      "Text": "Please provide the name of the lock manufacturer.",
      "UnixTime": 1589566051
    },
    {
      "Action": "utter",
      "Agent": "User",
      "Text": "seh si the manufcatured by ISS Alpha",
      "UnixTime": 1589566103
    },
    {
      "Action": "instruct",
      "Agent": "UserGuide",
      "Text": "Once the life support system is repaired (not earlier!), you can end the conversation.  [instruction 3 of 3]",
      "UnixTime": 1589566103
    },
    {
      "Action": "request_suggestions",
      "Agent": "Wizard",
      "Text": "cable",
      "UnixTime": 1589566116
    },
    {
      "Action": "utter",
      "Agent": "Wizard",
      "Text": "What are the cable colors?",
      "UnixTime": 1589566124
    },
    {
      "Action": "utter",
      "Agent": "User",
      "Text": "green and orange ",
      "UnixTime": 1589566152
    },
    {
      "APIName": "spaceship_life_support",
      "Action": "query",
      "Agent": "Wizard",
      "Constraints": [
        {
          "LockManufacturer": "\"ISS Alpha\""
        },
        {
          "ColorOfTopCable": "\"Green\""
        },
        {
          "ColorOfSecondCable": "\"Orange\""
        }
      ],
      "UnixTime": 1589566161
    },
    {
      "APIName": "spaceship_life_support",
      "Action": "return_item",
      "Agent": "KnowledgeBase",
      "Item": {
        "APIName": "spaceship_life_support",
        "Message": "Successful! Life support was recovered."
      },
      "TotalItems": -1
    },
    {
      "Action": "request_suggestions",
      "Agent": "Wizard",
      "PrimaryItem": {
        "APIName": "spaceship_life_support",
        "Message": "Successful! Life support was recovered."
      },
      "Text": "success",
      "UnixTime": 1589566164
    },
    {
      "Action": "pick_suggestion",
      "ActionLabel": "spaceship_inform_outcome",
      "ActionLabelOptions": [
        "spaceship_inform_outcome",
        "spaceship_bye",
        "hello"
      ],
      "Agent": "Wizard",
      "PrimaryItem": {
        "APIName": "spaceship_life_support",
        "Message": "Successful! Life support was recovered."
      },
      "Text": "Ok, I can reach the control panel now... Successful! Life support was recovered.",
      "UnixTime": 1589566167
    },
    {
      "Action": "utter",
      "Agent": "User",
      "Text": "thanks",
      "UnixTime": 1589566198
    },
    {
      "Action": "request_suggestions",
      "Agent": "Wizard",
      "PrimaryItem": {
        "APIName": "spaceship_life_support",
        "Message": "Successful! Life support was recovered."
      },
      "Text": "thank you",
      "UnixTime": 1589566203
    },
    {
      "Action": "pick_suggestion",
      "ActionLabel": "spaceship_bye",
      "ActionLabelOptions": [
        "spaceship_bye",
        "out_of_scope",
        "anything_else"
      ],
      "Agent": "Wizard",
      "PrimaryItem": {
        "APIName": "spaceship_life_support",
        "Message": "Successful! Life support was recovered."
      },
      "Text": "Goodbye.",
      "UnixTime": 1589566205
    },
    {
      "Action": "complete",
      "Agent": "User",
      "UnixTime": 1589566209
    }
  ],
  "FORMAT-VERSION": 7,
  "Scenario": {
    "Domains": [
      "spaceship"
    ],
    "Happy": true,
    "MultiTask": false,
    "UserTask": "The life support on your spaceship is failing! To save the lives of the crew, the ship's repair-robot has to get into the engineering deck, which is sealed due to a lack of air. Help the robot to enter the engineering deck! It has to temper with the lock (manufactured by 'ISS Alpha') and swap the positions of the Green cable and the Orange cable. It already reached the door.",
    "WizardCapabilities": [
      {
        "Domain": "spaceship",
        "SchemaImage": "spaceship_life_support.jpg",
        "Task": "spaceship_life_support"
      }
    ],
    "WizardTask": "Act as the spaceship's onboard robot and help the user recover the life support."
  },
  "UserQuestionnaire": [
    {
      "Answer": true,
      "Question": "Did the robot help successfully recover the life support?"
    },
    {
      "Answer": true,
      "Question": "Did the robot stay calm and helpful throughout the dialogue?"
    }
  ],
  "WizardQuestionnaire": [
    {
      "Answer": false,
      "Question": "Did the user change his/her mind about what he/she wants at any time?"
    },
    {
      "Answer": false,
      "Question": "Did the user become aggressive or annoyed during the dialogue? (Note: some users may be instructed to be annoying.)"
    },
    {
      "Answer": false,
      "Question": "Where you unsure about what to do at any time? (Feel free to send us an email with details.)"
    }
  ]
}