{
  "AnonymizedUserWorkerID": "58be375a-caa2-7735-72af-2683a9d7dda2",
  "AnonymizedWizardWorkerID": "6cb66f0b-1a8b-fec4-b481-96b6da01d513",
  "BatchID": "woz_1589554725",
  "CompletionLevel": "Complete",
  "DialogueID": 4805,
  "Events": [
    {
      "Action": "utter",
      "Agent": "User",
      "Text": "Hi I need a ride",
      "UnixTime": 1589600252
    },
    {
      "Action": "instruct",
      "Agent": "UserGuide",
      "Text": "You really need to be there soon. If the car takes more than 30 minutes to pick you up, ask for a different one. [instruction 1 of 5]",
      "UnixTime": 1589600252
    },
    {
      "Action": "request_suggestions",
      "Agent": "Wizard",
      "Text": "name",
      "UnixTime": 1589600259
    },
    {
      "Action": "pick_suggestion",
      "ActionLabel": "ask_name",
      "ActionLabelOptions": [
        "ask_name",
        "ride_inform_search_criteria",
        "ride_bye"
      ],
      "Agent": "Wizard",
      "Text": "May I have your name, please?",
      "UnixTime": 1589600261
    },
    {
      "Action": "utter",
      "Agent": "User",
      "Text": "Alexis",
      "UnixTime": 1589600265
    },
    {
      "Action": "instruct",
      "Agent": "UserGuide",
      "Text": "Say something about your hot date. Be creative! [instruction 2 of 5]",
      "UnixTime": 1589600265
    },
    {
      "Action": "request_suggestions",
      "Agent": "Wizard",
      "Text": "deppart",
      "UnixTime": 1589600271
    },
    {
      "Action": "request_suggestions",
      "Agent": "Wizard",
      "Text": "departure",
      "UnixTime": 1589600277
    },
    {
      "Action": "pick_suggestion",
      "ActionLabel": "ride_ask_departure",
      "ActionLabelOptions": [
        "ride_ask_departure",
        "ride_bye",
        "ride_inform_search_criteria"
      ],
      "Agent": "Wizard",
      "Text": "OK, and where are you departing from?",
      "UnixTime": 1589600279
    },
    {
      "Action": "utter",
      "Agent": "User",
      "Text": "I am departing from Forbes and Murray and I need to get to 5th and Main . I'm late for my date",
      "UnixTime": 1589600301
    },
    {
      "Action": "instruct",
      "Agent": "UserGuide",
      "Text": "If your ride is a Lyft, make sure your driver is not Mark. [instruction 3 of 5]",
      "UnixTime": 1589600301
    },
    {
      "APIName": "ride_book",
      "Action": "query",
      "Agent": "Wizard",
      "Constraints": [
        {
          "CustomerName": "\"Alexis\""
        },
        {
          "DepartureLocation": "\"Forbes and Murray\""
        },
        {
          "ArrivalLocation": "\"5th and Main\""
        },
        {
          "RequestType": "\"Check\""
        }
      ],
      "UnixTime": 1589600317
    },
    {
      "APIName": "ride_book",
      "Action": "return_item",
      "Agent": "KnowledgeBase",
      "Item": {
        "APIName": "ride_book",
        "AllowsChanges": true,
        "ArrivalLocation": "5th and Main",
        "CarModel": "Ford",
        "CustomerName": "Alexis",
        "DepartureLocation": "Forbes and Murray",
        "DriverName": "Dave",
        "LicensePlate": "901 FSA",
        "MinutesTillPickup": 26,
        "Price": 36,
        "ServiceProvider": "Taxi",
        "id": 294
      },
      "TotalItems": -1
    },
    {
      "Action": "request_suggestions",
      "Agent": "Wizard",
      "PrimaryItem": {
        "APIName": "ride_book",
        "AllowsChanges": true,
        "ArrivalLocation": "5th and Main",
        "CarModel": "Ford",
        "CustomerName": "Alexis",
        "DepartureLocation": "Forbes and Murray",
        "DriverName": "Dave",
        "LicensePlate": "901 FSA",
        "MinutesTillPickup": 26,
        "Price": 36,
        "ServiceProvider": "Taxi",
        "id": 294
      },
      "Text": "taxi",
      "UnixTime": 1589600321
    },
    {
      "Action": "pick_suggestion",
      "ActionLabel": "ride_ask_confirm_booking",
      "ActionLabelOptions": [
        "ride_ask_destination",
        "ride_ask_confirm_booking",
        "ride_inform_search_criteria"
      ],
      "Agent": "Wizard",
      "PrimaryItem": {
        "APIName": "ride_book",
        "AllowsChanges": true,
        "ArrivalLocation": "5th and Main",
        "CarModel": "Ford",
        "CustomerName": "Alexis",
        "DepartureLocation": "Forbes and Murray",
        "DriverName": "Dave",
        "LicensePlate": "901 FSA",
        "MinutesTillPickup": 26,
        "Price": 36,
        "ServiceProvider": "Taxi",
        "id": 294
      },
      "Text": "I found a Taxi ride for you from 'Forbes and Murray' to '5th and Main' for 36 credits\nthat could pick you up in 26 minutes. Should I book that for you?",
      "UnixTime": 1589600322
    },
    {
      "Action": "utter",
      "Agent": "User",
      "Text": "yes please. I'm so excited for this date! I need to get there on time. ",
      "UnixTime": 1589600343
    },
    {
      "Action": "instruct",
      "Agent": "UserGuide",
      "Text": "You realize that you are actually closer to Craig and Center right now. If you haven't booked yet, change your departure location to there. Otherwise, say something about the service provider of your ride. [instruction 4 of 5]",
      "UnixTime": 1589600343
    },
    {
      "APIName": "ride_book",
      "Action": "query",
      "Agent": "Wizard",
      "Constraints": [
        {
          "CustomerName": "\"Alexis\""
        },
        {
          "DepartureLocation": "\"Forbes and Murray\""
        },
        {
          "ArrivalLocation": "\"5th and Main\""
        },
        {
          "RequestType": "\"Book\""
        }
      ],
      "PrimaryItem": {
        "APIName": "ride_book",
        "AllowsChanges": true,
        "ArrivalLocation": "5th and Main",
        "CarModel": "Ford",
        "CustomerName": "Alexis",
        "DepartureLocation": "Forbes and Murray",
        "DriverName": "Dave",
        "LicensePlate": "901 FSA",
        "MinutesTillPickup": 26,
        "Price": 36,
        "ServiceProvider": "Taxi",
        "id": 294
      },
      "UnixTime": 1589600350
    },
    {
      "APIName": "ride_book",
      "Action": "return_item",
      "Agent": "KnowledgeBase",
      "Item": {
        "APIName": "ride_book",
        "Message": "Ride booked."
      },
      "TotalItems": -1
    },
    {
      "Action": "request_suggestions",
      "Agent": "Wizard",
      "PrimaryItem": {
        "APIName": "ride_book",
        "Message": "Ride booked."
      },
      "Text": "Confirmed booking, is there anything else I can do for you?",
      "UnixTime": 1589600370
    },
    {
      "Action": "utter",
      "Agent": "Wizard",
      "PrimaryItem": {
        "APIName": "ride_book",
        "Message": "Ride booked."
      },
      "Text": "Confirmed booking, is there anything else I can do for you?",
      "UnixTime": 1589600375
    },
    {
      "Action": "utter",
      "Agent": "User",
      "Text": "I'm just confirming my driver isn't named mark",
      "UnixTime": 1589600391
    },
    {
      "Action": "instruct",
      "Agent": "UserGuide",
      "Text": "Once you have found a ride that suits you, book it and talk some more about your hot date or make a joke. Then end the conversation. [instruction 5 of 5]",
      "UnixTime": 1589600391
    },
    {
      "Action": "request_suggestions",
      "Agent": "Wizard",
      "PrimaryItem": {
        "APIName": "ride_book",
        "Message": "Ride booked."
      },
      "Text": "Dave",
      "UnixTime": 1589600404
    },
    {
      "Action": "utter",
      "Agent": "Wizard",
      "PrimaryItem": {
        "APIName": "ride_book",
        "Message": "Ride booked."
      },
      "Text": "Your driver's name is Dave.",
      "UnixTime": 1589600422
    },
    {
      "Action": "utter",
      "Agent": "User",
      "Text": "great. Hope he drives fast! Can't miss this shot. thank you",
      "UnixTime": 1589600442
    },
    {
      "Action": "request_suggestions",
      "Agent": "Wizard",
      "PrimaryItem": {
        "APIName": "ride_book",
        "Message": "Ride booked."
      },
      "Text": "anything else",
      "UnixTime": 1589600449
    },
    {
      "Action": "pick_suggestion",
      "ActionLabel": "anything_else",
      "ActionLabelOptions": [
        "anything_else",
        "ride_bye",
        "ride_inform_nothing_found"
      ],
      "Agent": "Wizard",
      "PrimaryItem": {
        "APIName": "ride_book",
        "Message": "Ride booked."
      },
      "Text": "Is there anything else that I can do for you?",
      "UnixTime": 1589600451
    },
    {
      "Action": "utter",
      "Agent": "User",
      "Text": "that's all thanks",
      "UnixTime": 1589600459
    },
    {
      "Action": "request_suggestions",
      "Agent": "Wizard",
      "PrimaryItem": {
        "APIName": "ride_book",
        "Message": "Ride booked."
      },
      "Text": "thanks goodbye",
      "UnixTime": 1589600466
    },
    {
      "Action": "pick_suggestion",
      "ActionLabel": "ride_bye",
      "ActionLabelOptions": [
        "ride_bye",
        "ride_inform_search_criteria",
        "ride_inform_nothing_found"
      ],
      "Agent": "Wizard",
      "PrimaryItem": {
        "APIName": "ride_book",
        "Message": "Ride booked."
      },
      "Text": "Goodbye. Enjoy your ride!",
      "UnixTime": 1589600467
    },
    {
      "Action": "complete",
      "Agent": "User",
      "UnixTime": 1589600471
    }
  ],
  "FORMAT-VERSION": 7,
  "Scenario": {
    "Domains": [
      "ride"
    ],
    "Happy": true,
    "MultiTask": false,
    "UserTask": "You need a ride from 'Forbes and Murray' to '5th and Main' to get to your hot date. Your name is Alexis.",
    "WizardCapabilities": [
      {
        "Domain": "ride",
        "SchemaImage": "ride_book.jpg",
        "Task": "ride_book"
      }
    ],
    "WizardTask": "Help the user book a ride. "
  },
  "UserQuestionnaire": [
    {
      "Answer": true,
      "Question": "Did the assistant stay calm and helpful throughout the dialogue?"
    }
  ],
  "WizardQuestionnaire": [
    {
      "Answer": false,
      "Question": "Did the user change his/her mind about what he/she wants at any time?"
    },
    {
      "Answer": false,
      "Question": "Did the user become aggressive or annoyed during the dialogue? (Note: some users may be instructed to be annoying.)"
    },
    {
      "Answer": false,
      "Question": "Where you unsure about what to do at any time? (Feel free to send us an email with details.)"
    }
  ]
}