{
  "AnonymizedUserWorkerID": "3a5ea463-ded5-1b72-cab6-2e2ea04d6cf7",
  "AnonymizedWizardWorkerID": "a0362f23-a428-0712-805e-13fe4ea1da38",
  "BatchID": "woz_1590253362",
  "CompletionLevel": "Complete",
  "DialogueID": 4943,
  "Events": [
    {
      "Action": "instruct",
      "Agent": "UserGuide",
      "Text": "Maybe the AI Assistant can help? Say hello and ask if it can help you plan the party. [instruction 1 of 7]",
      "UnixTime": 1590257924
    },
    {
      "Action": "utter",
      "Agent": "User",
      "Text": "Hello",
      "UnixTime": 1590257944
    },
    {
      "Action": "instruct",
      "Agent": "UserGuide",
      "Text": "Alexis says: 'I think the North Heights Venue is quite nice'. [instruction 2 of 7]",
      "UnixTime": 1590257944
    },
    {
      "Action": "request_suggestions",
      "Agent": "Wizard",
      "Text": "hello",
      "UnixTime": 1590257949
    },
    {
      "Action": "pick_suggestion",
      "ActionLabel": "hello",
      "ActionLabelOptions": [
        "hello",
        "party_ask_day",
        "party_no_venue_available"
      ],
      "Agent": "Wizard",
      "Text": "Hello, how can I help?",
      "UnixTime": 1590257950
    },
    {
      "Action": "utter",
      "Agent": "User",
      "Text": "I am looking to plan a party",
      "UnixTime": 1590257983
    },
    {
      "Action": "request_suggestions",
      "Agent": "Wizard",
      "Text": "venue",
      "UnixTime": 1590257989
    },
    {
      "Action": "request_suggestions",
      "Agent": "Wizard",
      "Text": "which venue",
      "UnixTime": 1590257992
    },
    {
      "Action": "pick_suggestion",
      "ActionLabel": "party_ask_venue",
      "ActionLabelOptions": [
        "party_ask_venue",
        "party_booking_failed",
        "party_ask_drinks"
      ],
      "Agent": "Wizard",
      "Text": "At what venue would you like to have your party organised?",
      "UnixTime": 1590257994
    },
    {
      "Action": "utter",
      "Agent": "User",
      "Text": "North Heights Venue should work",
      "UnixTime": 1590258059
    },
    {
      "Action": "instruct",
      "Agent": "UserGuide",
      "Text": "It occurs to you that if the weather is nice, you might just have the party outside somewhere. Ask your assistant what the weather will be like on Sunday. [instruction 3 of 7]",
      "UnixTime": 1590258059
    },
    {
      "Action": "request_suggestions",
      "Agent": "Wizard",
      "Text": "name",
      "UnixTime": 1590258063
    },
    {
      "Action": "pick_suggestion",
      "ActionLabel": "ask_name",
      "ActionLabelOptions": [
        "ask_name",
        "party_bye",
        "out_of_scope"
      ],
      "Agent": "Wizard",
      "Text": "May I have your name, please?",
      "UnixTime": 1590258065
    },
    {
      "Action": "utter",
      "Agent": "User",
      "Text": "Ben here",
      "UnixTime": 1590258076
    },
    {
      "Action": "instruct",
      "Agent": "UserGuide",
      "Text": "Alexis says: 'Yeah, actually, if the weather is good, we could just go out to the park and book a restaurant for the evening'. You agree. So depending on the weather, either continue searching / booking the venue, or ask your assistant to help you find and book a restaurant for Sunday evening. [instruction 4 of 7]",
      "UnixTime": 1590258076
    },
    {
      "Action": "request_suggestions",
      "Agent": "Wizard",
      "Text": "day",
      "UnixTime": 1590258080
    },
    {
      "Action": "pick_suggestion",
      "ActionLabel": "party_ask_day",
      "ActionLabelOptions": [
        "party_ask_day",
        "party_ask_number_of_guests",
        "party_bye"
      ],
      "Agent": "Wizard",
      "Text": "On what day would you like your party organised?",
      "UnixTime": 1590258082
    },
    {
      "Action": "utter",
      "Agent": "User",
      "Text": "Sunday",
      "UnixTime": 1590258091
    },
    {
      "Action": "instruct",
      "Agent": "UserGuide",
      "Text": "Note: You are located in the Center of town, which you may or may not take into account if you search for a restaurant. [instruction 5 of 7]",
      "UnixTime": 1590258091
    },
    {
      "Action": "request_suggestions",
      "Agent": "Wizard",
      "Text": "when kick off",
      "UnixTime": 1590258095
    },
    {
      "Action": "pick_suggestion",
      "ActionLabel": "party_ask_starting_time",
      "ActionLabelOptions": [
        "party_ask_end_time",
        "party_ask_starting_time",
        "party_inform_food_drink_criteria"
      ],
      "Agent": "Wizard",
      "Text": "When would you like your party to kick off?",
      "UnixTime": 1590258098
    },
    {
      "Action": "utter",
      "Agent": "User",
      "Text": "Wait a sec, if it's nice weather we might actually host it outside. Can you check to the weather for Sunday please?",
      "UnixTime": 1590258130
    },
    {
      "Action": "instruct",
      "Agent": "UserGuide",
      "Text": "When the question comes up: you both like Chinese food and Indian food, but no Thai food. [instruction 6 of 7]",
      "UnixTime": 1590258130
    },
    {
      "Action": "select_task",
      "Agent": "Wizard",
      "Task": "weather",
      "UnixTime": 1590258130
    },
    {
      "APIName": "weather",
      "Action": "query",
      "Agent": "Wizard",
      "Constraints": [
        {
          "Day": "api.is_equal_to(\"Sunday\")"
        }
      ],
      "UnixTime": 1590258132
    },
    {
      "APIName": "weather",
      "Action": "return_item",
      "Agent": "KnowledgeBase",
      "Item": {
        "APIName": "weather",
        "City": "Pittsburgh",
        "Day": "Sunday",
        "TemperatureCelsius": 20,
        "Weather": "Raining",
        "id": 677
      },
      "TotalItems": -1
    },
    {
      "Action": "request_suggestions",
      "Agent": "Wizard",
      "PrimaryItem": {
        "APIName": "weather",
        "City": "Pittsburgh",
        "Day": "Sunday",
        "TemperatureCelsius": 20,
        "Weather": "Raining",
        "id": 677
      },
      "Text": "raining",
      "UnixTime": 1590258136
    },
    {
      "Action": "pick_suggestion",
      "ActionLabel": "weather_inform_forecast",
      "ActionLabelOptions": [
        "weather_bye",
        "weather_ask_location",
        "weather_inform_forecast"
      ],
      "Agent": "Wizard",
      "PrimaryItem": {
        "APIName": "weather",
        "City": "Pittsburgh",
        "Day": "Sunday",
        "TemperatureCelsius": 20,
        "Weather": "Raining",
        "id": 677
      },
      "Text": "It will be Raining all day on Sunday in Pittsburgh, with temperatures of around 20 degrees celsius.",
      "UnixTime": 1590258137
    },
    {
      "Action": "utter",
      "Agent": "User",
      "Text": "Oh, forget that then. We'll have it at the North Heights then",
      "UnixTime": 1590258161
    },
    {
      "Action": "select_task",
      "Agent": "Wizard",
      "PrimaryItem": {
        "APIName": "weather",
        "City": "Pittsburgh",
        "Day": "Sunday",
        "TemperatureCelsius": 20,
        "Weather": "Raining",
        "id": 677
      },
      "Task": "party_plan",
      "UnixTime": 1590258161
    },
    {
      "Action": "request_suggestions",
      "Agent": "Wizard",
      "PrimaryItem": {
        "APIName": "weather",
        "City": "Pittsburgh",
        "Day": "Sunday",
        "TemperatureCelsius": 20,
        "Weather": "Raining",
        "id": 677
      },
      "Text": "when kick off",
      "UnixTime": 1590258172
    },
    {
      "Action": "pick_suggestion",
      "ActionLabel": "party_ask_starting_time",
      "ActionLabelOptions": [
        "party_ask_end_time",
        "party_ask_starting_time",
        "weather_ask_day",
        "weather_bye",
        "out_of_scope",
        "party_inform_food_drink_criteria"
      ],
      "Agent": "Wizard",
      "PrimaryItem": {
        "APIName": "weather",
        "City": "Pittsburgh",
        "Day": "Sunday",
        "TemperatureCelsius": 20,
        "Weather": "Raining",
        "id": 677
      },
      "Text": "When would you like your party to kick off?",
      "UnixTime": 1590258174
    },
    {
      "Action": "utter",
      "Agent": "User",
      "Text": "Let's go with 7pm",
      "UnixTime": 1590258183
    },
    {
      "Action": "request_suggestions",
      "Agent": "Wizard",
      "PrimaryItem": {
        "APIName": "weather",
        "City": "Pittsburgh",
        "Day": "Sunday",
        "TemperatureCelsius": 20,
        "Weather": "Raining",
        "id": 677
      },
      "Text": "guests",
      "UnixTime": 1590258185
    },
    {
      "Action": "pick_suggestion",
      "ActionLabel": "party_ask_number_of_guests",
      "ActionLabelOptions": [
        "party_ask_number_of_guests",
        "weather_ask_location",
        "weather_inform_forecast",
        "anything_else",
        "out_of_scope",
        "party_bye"
      ],
      "Agent": "Wizard",
      "PrimaryItem": {
        "APIName": "weather",
        "City": "Pittsburgh",
        "Day": "Sunday",
        "TemperatureCelsius": 20,
        "Weather": "Raining",
        "id": 677
      },
      "Text": "How many people would you like to invite?",
      "UnixTime": 1590258187
    },
    {
      "Action": "utter",
      "Agent": "User",
      "Text": "79 people. It's a big one",
      "UnixTime": 1590258198
    },
    {
      "Action": "instruct",
      "Agent": "UserGuide",
      "Text": "When you are done booking (not just finding!) either a restaurant or a party venue, you can say goodbye and end the dialogue. This might take a while though, e.g. in case the venue is not available. [instruction 7 of 7]",
      "UnixTime": 1590258198
    },
    {
      "APIName": "party_plan",
      "Action": "query",
      "Agent": "Wizard",
      "Constraints": [
        {
          "Name": "\"North Heights Venue\""
        },
        {
          "HostName": "\"Ben\""
        },
        {
          "Day": "api.is_equal_to(\"Sunday\")"
        },
        {
          "StartTimeHour": "\"7 pm\""
        },
        {
          "NumberGuests": "79"
        },
        {
          "RequestType": "\"Check\""
        }
      ],
      "PrimaryItem": {
        "APIName": "weather",
        "City": "Pittsburgh",
        "Day": "Sunday",
        "TemperatureCelsius": 20,
        "Weather": "Raining",
        "id": 677
      },
      "UnixTime": 1590258203
    },
    {
      "APIName": "party_plan",
      "Action": "return_item",
      "Agent": "KnowledgeBase",
      "Item": {
        "APIName": "party_plan",
        "Day": "Sunday",
        "Message": "The venue is available.",
        "Time": "7 pm",
        "VenueName": "North Heights Venue"
      },
      "TotalItems": -1
    },
    {
      "Action": "request_suggestions",
      "Agent": "Wizard",
      "PrimaryItem": {
        "APIName": "party_plan",
        "Day": "Sunday",
        "Message": "The venue is available.",
        "Time": "7 pm",
        "VenueName": "North Heights Venue"
      },
      "Text": "available",
      "UnixTime": 1590258208
    },
    {
      "Action": "pick_suggestion",
      "ActionLabel": "party_ask_confirm_booking",
      "ActionLabelOptions": [
        "party_ask_confirm_booking",
        "party_ask_day",
        "party_booking_successful"
      ],
      "Agent": "Wizard",
      "PrimaryItem": {
        "APIName": "party_plan",
        "Day": "Sunday",
        "Message": "The venue is available.",
        "Time": "7 pm",
        "VenueName": "North Heights Venue"
      },
      "Text": "OK, the North Heights Venue would be happy to accommodate you on Sunday @ 7 pm.\nCan I book it for you now?",
      "UnixTime": 1590258210
    },
    {
      "Action": "utter",
      "Agent": "User",
      "Text": "Yes please!",
      "UnixTime": 1590258219
    },
    {
      "APIName": "party_plan",
      "Action": "query",
      "Agent": "Wizard",
      "Constraints": [
        {
          "Name": "\"North Heights Venue\""
        },
        {
          "HostName": "\"Ben\""
        },
        {
          "Day": "api.is_equal_to(\"Sunday\")"
        },
        {
          "StartTimeHour": "\"7 pm\""
        },
        {
          "NumberGuests": "79"
        },
        {
          "RequestType": "\"Book\""
        }
      ],
      "PrimaryItem": {
        "APIName": "party_plan",
        "Day": "Sunday",
        "Message": "The venue is available.",
        "Time": "7 pm",
        "VenueName": "North Heights Venue"
      },
      "UnixTime": 1590258222
    },
    {
      "APIName": "party_plan",
      "Action": "return_item",
      "Agent": "KnowledgeBase",
      "Item": {
        "APIName": "party_plan",
        "Day": "Sunday",
        "Message": "Your event has been successfully scheduled.",
        "Time": "7 pm",
        "VenueName": "North Heights Venue"
      },
      "TotalItems": -1
    },
    {
      "Action": "request_suggestions",
      "Agent": "Wizard",
      "PrimaryItem": {
        "APIName": "party_plan",
        "Day": "Sunday",
        "Message": "Your event has been successfully scheduled.",
        "Time": "7 pm",
        "VenueName": "North Heights Venue"
      },
      "Text": "Your event has been successfully scheduled",
      "UnixTime": 1590258227
    },
    {
      "Action": "pick_suggestion",
      "ActionLabel": "party_booking_successful",
      "ActionLabelOptions": [
        "party_booking_successful",
        "party_ask_food",
        "hello"
      ],
      "Agent": "Wizard",
      "PrimaryItem": {
        "APIName": "party_plan",
        "Day": "Sunday",
        "Message": "Your event has been successfully scheduled.",
        "Time": "7 pm",
        "VenueName": "North Heights Venue"
      },
      "Text": "Great, your party has been successfully booked at the North Heights Venue on Sunday at 7 pm!",
      "UnixTime": 1590258229
    },
    {
      "Action": "utter",
      "Agent": "User",
      "Text": "Thanks so much! take care",
      "UnixTime": 1590258236
    },
    {
      "Action": "request_suggestions",
      "Agent": "Wizard",
      "PrimaryItem": {
        "APIName": "party_plan",
        "Day": "Sunday",
        "Message": "Your event has been successfully scheduled.",
        "Time": "7 pm",
        "VenueName": "North Heights Venue"
      },
      "Text": "bye",
      "UnixTime": 1590258243
    },
    {
      "Action": "pick_suggestion",
      "ActionLabel": "party_bye",
      "ActionLabelOptions": [
        "party_bye",
        "party_ask_end_time",
        "out_of_scope"
      ],
      "Agent": "Wizard",
      "PrimaryItem": {
        "APIName": "party_plan",
        "Day": "Sunday",
        "Message": "Your event has been successfully scheduled.",
        "Time": "7 pm",
        "VenueName": "North Heights Venue"
      },
      "Text": "Thank you and goodbye.",
      "UnixTime": 1590258247
    },
    {
      "Action": "complete",
      "Agent": "User",
      "UnixTime": 1590258254
    }
  ],
  "FORMAT-VERSION": 7,
  "Scenario": {
    "Domains": [
      "party",
      "restaurant",
      "weather"
    ],
    "Happy": false,
    "MultiTask": true,
    "UserTask": "You (Ben) and your friend Alexis want to organize a birthday party on Sunday. You expect 79 guests to come.",
    "WizardCapabilities": [
      {
        "Domain": "party",
        "SchemaImage": "party_plan.jpg",
        "Task": "party_plan"
      },
      {
        "Domain": "weather",
        "SchemaImage": "weather.jpg",
        "Task": "weather"
      },
      {
        "Domain": "restaurant",
        "SchemaImage": "restaurant_search.jpg",
        "Task": "restaurant_search"
      },
      {
        "Domain": "restaurant",
        "SchemaImage": "restaurant_book.jpg",
        "Task": "restaurant_book"
      }
    ],
    "WizardTask": "Follow the flow charts and help the user. Note: If the user already knows a restaurant name, use 'restaurant reserve', otherwise use 'restaurant search'."
  },
  "UserQuestionnaire": [
    {
      "Answer": true,
      "Question": "Did the assistant stay calm and helpful throughout the dialogue?"
    }
  ],
  "WizardQuestionnaire": [
    {
      "Answer": false,
      "Question": "Did the user change his/her mind about what he/she wants at any time?"
    },
    {
      "Answer": false,
      "Question": "Did the user become aggressive or annoyed during the dialogue? (Note: some users may be instructed to be annoying.)"
    },
    {
      "Answer": false,
      "Question": "Where you unsure about what to do at any time? (Feel free to send us an email with details.)"
    }
  ]
}