{
  "AnonymizedUserWorkerID": "73cd3146-78b3-8662-261e-62d39ac21292",
  "AnonymizedWizardWorkerID": "eae96765-3d74-8647-cc03-fc417533d9b1",
  "BatchID": "woz_1590426434",
  "CompletionLevel": "Complete",
  "DialogueID": 760,
  "Events": [
    {
      "Action": "utter",
      "Agent": "User",
      "Text": "hello. i want to search  Hilton Hotel near the North part of town and note its rating",
      "UnixTime": 1590432024
    },
    {
      "APIName": "hotel_search",
      "Action": "query",
      "Agent": "Wizard",
      "Constraints": [
        {
          "Name": "\"Hilton Hotel\""
        },
        {
          "Location": "\"North\""
        }
      ],
      "UnixTime": 1590432063
    },
    {
      "APIName": "hotel_search",
      "Action": "return_item",
      "Agent": "KnowledgeBase",
      "Item": {
        "APIName": "hotel_search",
        "AverageRating": 4,
        "Cost": "Cheap",
        "Location": "North",
        "Name": "Hilton Hotel",
        "Service": true,
        "ServiceStartHour": "7 am",
        "ServiceStopHour": "11 pm",
        "TakesReservations": false,
        "id": 195
      },
      "TotalItems": 55
    },
    {
      "Action": "request_suggestions",
      "Agent": "Wizard",
      "PrimaryItem": {
        "APIName": "hotel_search",
        "AverageRating": 4,
        "Cost": "Cheap",
        "Location": "North",
        "Name": "Hilton Hotel",
        "Service": true,
        "ServiceStartHour": "7 am",
        "ServiceStopHour": "11 pm",
        "TakesReservations": false,
        "id": 195
      },
      "Text": "hilton north 4 rating",
      "UnixTime": 1590432071
    },
    {
      "Action": "request_suggestions",
      "Agent": "Wizard",
      "PrimaryItem": {
        "APIName": "hotel_search",
        "AverageRating": 4,
        "Cost": "Cheap",
        "Location": "North",
        "Name": "Hilton Hotel",
        "Service": true,
        "ServiceStartHour": "7 am",
        "ServiceStopHour": "11 pm",
        "TakesReservations": false,
        "id": 195
      },
      "Text": "There is a hilton north",
      "UnixTime": 1590432076
    },
    {
      "Action": "pick_suggestion",
      "ActionLabel": "hotel_provide_search_result",
      "ActionLabelOptions": [
        "hotel_provide_search_result",
        "hotel_inform_name",
        "hotel_inform_location"
      ],
      "Agent": "Wizard",
      "PrimaryItem": {
        "APIName": "hotel_search",
        "AverageRating": 4,
        "Cost": "Cheap",
        "Location": "North",
        "Name": "Hilton Hotel",
        "Service": true,
        "ServiceStartHour": "7 am",
        "ServiceStopHour": "11 pm",
        "TakesReservations": false,
        "id": 195
      },
      "Text": "OK, I have found the 'Hilton Hotel', located North. It is in the Cheap price category and has an average rating of 4.",
      "UnixTime": 1590432078
    },
    {
      "Action": "utter",
      "Agent": "User",
      "Text": "that sounds great.",
      "UnixTime": 1590432105
    },
    {
      "Action": "instruct",
      "Agent": "UserGuide",
      "Text": "You just remember from a previous visit that the North of town is typically very noisy. Make sure to check whether there is a Hilton Hotel in the East part of town and note down its rating. [instruction 1 of 6]",
      "UnixTime": 1590432105
    },
    {
      "Action": "request_suggestions",
      "Agent": "Wizard",
      "PrimaryItem": {
        "APIName": "hotel_search",
        "AverageRating": 4,
        "Cost": "Cheap",
        "Location": "North",
        "Name": "Hilton Hotel",
        "Service": true,
        "ServiceStartHour": "7 am",
        "ServiceStopHour": "11 pm",
        "TakesReservations": false,
        "id": 195
      },
      "Text": "continue search?",
      "UnixTime": 1590432128
    },
    {
      "Action": "request_suggestions",
      "Agent": "Wizard",
      "PrimaryItem": {
        "APIName": "hotel_search",
        "AverageRating": 4,
        "Cost": "Cheap",
        "Location": "North",
        "Name": "Hilton Hotel",
        "Service": true,
        "ServiceStartHour": "7 am",
        "ServiceStopHour": "11 pm",
        "TakesReservations": false,
        "id": 195
      },
      "Text": "should I continue searching?",
      "UnixTime": 1590432134
    },
    {
      "Action": "pick_suggestion",
      "ActionLabel": "hotel_ask_search_more",
      "ActionLabelOptions": [
        "hotel_ask_search_more",
        "anything_else",
        "hotel_ask_rating"
      ],
      "Agent": "Wizard",
      "PrimaryItem": {
        "APIName": "hotel_search",
        "AverageRating": 4,
        "Cost": "Cheap",
        "Location": "North",
        "Name": "Hilton Hotel",
        "Service": true,
        "ServiceStartHour": "7 am",
        "ServiceStopHour": "11 pm",
        "TakesReservations": false,
        "id": 195
      },
      "Text": "Would you like to search for any more hotels?",
      "UnixTime": 1590432136
    },
    {
      "Action": "utter",
      "Agent": "User",
      "Text": "i just remembered the North one is very noisy.",
      "UnixTime": 1590432182
    },
    {
      "Action": "instruct",
      "Agent": "UserGuide",
      "Text": "Actually, you remember reading on a blog that the West of town is very trendy at the moment, check whether there is a Hilton Hotel in the West part of town and note down its rating. [instruction 2 of 6]",
      "UnixTime": 1590432182
    },
    {
      "Action": "request_suggestions",
      "Agent": "Wizard",
      "PrimaryItem": {
        "APIName": "hotel_search",
        "AverageRating": 4,
        "Cost": "Cheap",
        "Location": "North",
        "Name": "Hilton Hotel",
        "Service": true,
        "ServiceStartHour": "7 am",
        "ServiceStopHour": "11 pm",
        "TakesReservations": false,
        "id": 195
      },
      "Text": "search again?",
      "UnixTime": 1590432232
    },
    {
      "Action": "pick_suggestion",
      "ActionLabel": "hotel_ask_search_more",
      "ActionLabelOptions": [
        "hotel_inform_nothing_found",
        "hotel_ask_search_more",
        "anything_else"
      ],
      "Agent": "Wizard",
      "PrimaryItem": {
        "APIName": "hotel_search",
        "AverageRating": 4,
        "Cost": "Cheap",
        "Location": "North",
        "Name": "Hilton Hotel",
        "Service": true,
        "ServiceStartHour": "7 am",
        "ServiceStopHour": "11 pm",
        "TakesReservations": false,
        "id": 195
      },
      "Text": "Would you like to search for any more hotels?",
      "UnixTime": 1590432234
    },
    {
      "Action": "utter",
      "Agent": "User",
      "Text": "check out for one in the east part",
      "UnixTime": 1590432260
    },
    {
      "Action": "instruct",
      "Agent": "UserGuide",
      "Text": "You remember that your partner is not a fan of the franchise to which the Hilton Hotel belongs to. Ask the assistant about the rating of the Hyatt Hotel in the West part of town. [instruction 3 of 6]",
      "UnixTime": 1590432260
    },
    {
      "APIName": "hotel_search",
      "Action": "query",
      "Agent": "Wizard",
      "Constraints": [
        {
          "Name": "\"Hilton Hotel\""
        },
        {
          "Location": "\"East\""
        }
      ],
      "PrimaryItem": {
        "APIName": "hotel_search",
        "AverageRating": 4,
        "Cost": "Cheap",
        "Location": "North",
        "Name": "Hilton Hotel",
        "Service": true,
        "ServiceStartHour": "7 am",
        "ServiceStopHour": "11 pm",
        "TakesReservations": false,
        "id": 195
      },
      "UnixTime": 1590432264
    },
    {
      "APIName": "hotel_search",
      "Action": "return_item",
      "Agent": "KnowledgeBase",
      "Item": {
        "APIName": "hotel_search",
        "AverageRating": 3,
        "Cost": "Cheap",
        "Location": "East",
        "Name": "Hilton Hotel",
        "Service": false,
        "TakesReservations": false,
        "id": 655
      },
      "TotalItems": 55
    },
    {
      "Action": "request_suggestions",
      "Agent": "Wizard",
      "PrimaryItem": {
        "APIName": "hotel_search",
        "AverageRating": 3,
        "Cost": "Cheap",
        "Location": "East",
        "Name": "Hilton Hotel",
        "Service": false,
        "TakesReservations": false,
        "id": 655
      },
      "Text": "There is hilton in east cheap",
      "UnixTime": 1590432272
    },
    {
      "Action": "pick_suggestion",
      "ActionLabel": "hotel_provide_search_result",
      "ActionLabelOptions": [
        "hotel_provide_search_result",
        "hotel_inform_name",
        "hotel_inform_price"
      ],
      "Agent": "Wizard",
      "PrimaryItem": {
        "APIName": "hotel_search",
        "AverageRating": 3,
        "Cost": "Cheap",
        "Location": "East",
        "Name": "Hilton Hotel",
        "Service": false,
        "TakesReservations": false,
        "id": 655
      },
      "Text": "OK, I have found the 'Hilton Hotel', located East. It is in the Cheap price category and has an average rating of 3.",
      "UnixTime": 1590432274
    },
    {
      "Action": "utter",
      "Agent": "User",
      "Text": "can you also check for the one in the west too please.",
      "UnixTime": 1590432310
    },
    {
      "Action": "instruct",
      "Agent": "UserGuide",
      "Text": "Make some smalltalk about things you're planning to do in town such as museums you want to see, concerts you want to go to, or bars and restaurants you are excited about. Be creative. [instruction 4 of 6]",
      "UnixTime": 1590432310
    },
    {
      "APIName": "hotel_search",
      "Action": "query",
      "Agent": "Wizard",
      "Constraints": [
        {
          "Name": "\"Hilton Hotel\""
        },
        {
          "Location": "\"West\""
        }
      ],
      "PrimaryItem": {
        "APIName": "hotel_search",
        "AverageRating": 3,
        "Cost": "Cheap",
        "Location": "East",
        "Name": "Hilton Hotel",
        "Service": false,
        "TakesReservations": false,
        "id": 655
      },
      "UnixTime": 1590432315
    },
    {
      "APIName": "hotel_search",
      "Action": "return_item",
      "Agent": "KnowledgeBase",
      "Item": {
        "APIName": "hotel_search",
        "AverageRating": 5,
        "Cost": "Expensive",
        "Location": "West",
        "Name": "Hilton Hotel",
        "Service": false,
        "TakesReservations": false,
        "id": 528
      },
      "TotalItems": 43
    },
    {
      "Action": "request_suggestions",
      "Agent": "Wizard",
      "PrimaryItem": {
        "APIName": "hotel_search",
        "AverageRating": 5,
        "Cost": "Expensive",
        "Location": "West",
        "Name": "Hilton Hotel",
        "Service": false,
        "TakesReservations": false,
        "id": 528
      },
      "Text": "There is hilton in west expensive",
      "UnixTime": 1590432321
    },
    {
      "Action": "pick_suggestion",
      "ActionLabel": "hotel_provide_search_result",
      "ActionLabelOptions": [
        "hotel_provide_search_result",
        "hotel_inform_name",
        "hotel_inform_price"
      ],
      "Agent": "Wizard",
      "PrimaryItem": {
        "APIName": "hotel_search",
        "AverageRating": 5,
        "Cost": "Expensive",
        "Location": "West",
        "Name": "Hilton Hotel",
        "Service": false,
        "TakesReservations": false,
        "id": 528
      },
      "Text": "OK, I have found the 'Hilton Hotel', located West. It is in the Expensive price category and has an average rating of 5.",
      "UnixTime": 1590432322
    },
    {
      "Action": "utter",
      "Agent": "User",
      "Text": "my partner does not like the franchise to which the Hilton Hotel belongs to. can you please check out for the Hyatt Hotel in the West part of town. I want a place for a perfect date ",
      "UnixTime": 1590432444
    },
    {
      "Action": "instruct",
      "Agent": "UserGuide",
      "Text": "You remember a friend stayed at the Shadyside Inn before - compare the rating of the Hyatt Hotel to that of the Shadyside Inn in the West part of town. [instruction 5 of 6]",
      "UnixTime": 1590432444
    },
    {
      "APIName": "hotel_search",
      "Action": "query",
      "Agent": "Wizard",
      "Constraints": [
        {
          "Name": "\"Hyatt Hotel\""
        },
        {
          "Location": "\"West\""
        }
      ],
      "PrimaryItem": {
        "APIName": "hotel_search",
        "AverageRating": 5,
        "Cost": "Expensive",
        "Location": "West",
        "Name": "Hilton Hotel",
        "Service": false,
        "TakesReservations": false,
        "id": 528
      },
      "UnixTime": 1590432454
    },
    {
      "APIName": "hotel_search",
      "Action": "return_item",
      "Agent": "KnowledgeBase",
      "Item": {
        "APIName": "hotel_search",
        "AverageRating": 5,
        "Cost": "Cheap",
        "Location": "West",
        "Name": "Hyatt Hotel",
        "Service": true,
        "ServiceStartHour": "1 am",
        "ServiceStopHour": "10 pm",
        "TakesReservations": false,
        "id": 368
      },
      "TotalItems": 45
    },
    {
      "Action": "request_suggestions",
      "Agent": "Wizard",
      "PrimaryItem": {
        "APIName": "hotel_search",
        "AverageRating": 5,
        "Cost": "Cheap",
        "Location": "West",
        "Name": "Hyatt Hotel",
        "Service": true,
        "ServiceStartHour": "1 am",
        "ServiceStopHour": "10 pm",
        "TakesReservations": false,
        "id": 368
      },
      "Text": "hyatt west cheap",
      "UnixTime": 1590432460
    },
    {
      "Action": "request_suggestions",
      "Agent": "Wizard",
      "PrimaryItem": {
        "APIName": "hotel_search",
        "AverageRating": 5,
        "Cost": "Cheap",
        "Location": "West",
        "Name": "Hyatt Hotel",
        "Service": true,
        "ServiceStartHour": "1 am",
        "ServiceStopHour": "10 pm",
        "TakesReservations": false,
        "id": 368
      },
      "Text": "There is hyatt in the west cheap price",
      "UnixTime": 1590432467
    },
    {
      "Action": "pick_suggestion",
      "ActionLabel": "hotel_provide_search_result",
      "ActionLabelOptions": [
        "hotel_inform_name",
        "hotel_provide_search_result",
        "hotel_inform_price"
      ],
      "Agent": "Wizard",
      "PrimaryItem": {
        "APIName": "hotel_search",
        "AverageRating": 5,
        "Cost": "Cheap",
        "Location": "West",
        "Name": "Hyatt Hotel",
        "Service": true,
        "ServiceStartHour": "1 am",
        "ServiceStopHour": "10 pm",
        "TakesReservations": false,
        "id": 368
      },
      "Text": "OK, I have found the 'Hyatt Hotel', located West. It is in the Cheap price category and has an average rating of 5.",
      "UnixTime": 1590432469
    },
    {
      "Action": "utter",
      "Agent": "User",
      "Text": "can you please compare it to Shadyside Inn in terms of their rating?",
      "UnixTime": 1590432517
    },
    {
      "Action": "instruct",
      "Agent": "UserGuide",
      "Text": "Thank the assistant for their help and bring the conversation to a natural end. [instruction 6 of 6]",
      "UnixTime": 1590432517
    },
    {
      "APIName": "hotel_search",
      "Action": "query",
      "Agent": "Wizard",
      "Constraints": [
        {
          "Name": "\"Shadyside Inn\""
        },
        {
          "Location": "\"West\""
        }
      ],
      "PrimaryItem": {
        "APIName": "hotel_search",
        "AverageRating": 5,
        "Cost": "Cheap",
        "Location": "West",
        "Name": "Hyatt Hotel",
        "Service": true,
        "ServiceStartHour": "1 am",
        "ServiceStopHour": "10 pm",
        "TakesReservations": false,
        "id": 368
      },
      "UnixTime": 1590432534
    },
    {
      "APIName": "hotel_search",
      "Action": "return_item",
      "Agent": "KnowledgeBase",
      "Item": {
        "APIName": "hotel_search",
        "AverageRating": 3,
        "Cost": "Moderate",
        "Location": "West",
        "Name": "Shadyside Inn",
        "Service": false,
        "TakesReservations": false,
        "id": 223
      },
      "TotalItems": 39
    },
    {
      "Action": "select_secondary",
      "Agent": "Wizard",
      "PrimaryItem": {
        "APIName": "hotel_search",
        "AverageRating": 3,
        "Cost": "Moderate",
        "Location": "West",
        "Name": "Shadyside Inn",
        "Service": false,
        "TakesReservations": false,
        "id": 223
      },
      "UnixTime": 1590432538
    },
    {
      "Action": "request_suggestions",
      "Agent": "Wizard",
      "PrimaryItem": {
        "APIName": "hotel_search",
        "AverageRating": 3,
        "Cost": "Moderate",
        "Location": "West",
        "Name": "Shadyside Inn",
        "Service": false,
        "TakesReservations": false,
        "id": 223
      },
      "SecondaryItem": {
        "APIName": "hotel_search",
        "AverageRating": 5,
        "Cost": "Cheap",
        "Location": "West",
        "Name": "Hyatt Hotel",
        "Service": true,
        "ServiceStartHour": "1 am",
        "ServiceStopHour": "10 pm",
        "TakesReservations": false,
        "id": 368
      },
      "Text": "shadyside inn has a rating of 3",
      "UnixTime": 1590432557
    },
    {
      "Action": "pick_suggestion",
      "ActionLabel": "hotel_provide_search_result",
      "ActionLabelOptions": [
        "hotel_inform_rating",
        "hotel_provide_search_result",
        "hotel_inform_name"
      ],
      "Agent": "Wizard",
      "PrimaryItem": {
        "APIName": "hotel_search",
        "AverageRating": 3,
        "Cost": "Moderate",
        "Location": "West",
        "Name": "Shadyside Inn",
        "Service": false,
        "TakesReservations": false,
        "id": 223
      },
      "SecondaryItem": {
        "APIName": "hotel_search",
        "AverageRating": 5,
        "Cost": "Cheap",
        "Location": "West",
        "Name": "Hyatt Hotel",
        "Service": true,
        "ServiceStartHour": "1 am",
        "ServiceStopHour": "10 pm",
        "TakesReservations": false,
        "id": 368
      },
      "Text": "OK, I have found the 'Shadyside Inn', located West. It is in the Moderate price category and has an average rating of 3.",
      "UnixTime": 1590432562
    },
    {
      "Action": "utter",
      "Agent": "User",
      "Text": "thanks a lot for your help",
      "UnixTime": 1590432595
    },
    {
      "Action": "request_suggestions",
      "Agent": "Wizard",
      "PrimaryItem": {
        "APIName": "hotel_search",
        "AverageRating": 3,
        "Cost": "Moderate",
        "Location": "West",
        "Name": "Shadyside Inn",
        "Service": false,
        "TakesReservations": false,
        "id": 223
      },
      "SecondaryItem": {
        "APIName": "hotel_search",
        "AverageRating": 5,
        "Cost": "Cheap",
        "Location": "West",
        "Name": "Hyatt Hotel",
        "Service": true,
        "ServiceStartHour": "1 am",
        "ServiceStopHour": "10 pm",
        "TakesReservations": false,
        "id": 368
      },
      "Text": "anything else?",
      "UnixTime": 1590432601
    },
    {
      "Action": "pick_suggestion",
      "ActionLabel": "anything_else",
      "ActionLabelOptions": [
        "anything_else",
        "hotel_inform_nothing_found",
        "hotel_ask_search_more"
      ],
      "Agent": "Wizard",
      "PrimaryItem": {
        "APIName": "hotel_search",
        "AverageRating": 3,
        "Cost": "Moderate",
        "Location": "West",
        "Name": "Shadyside Inn",
        "Service": false,
        "TakesReservations": false,
        "id": 223
      },
      "SecondaryItem": {
        "APIName": "hotel_search",
        "AverageRating": 5,
        "Cost": "Cheap",
        "Location": "West",
        "Name": "Hyatt Hotel",
        "Service": true,
        "ServiceStartHour": "1 am",
        "ServiceStopHour": "10 pm",
        "TakesReservations": false,
        "id": 368
      },
      "Text": "Is there anything else that I can do for you?",
      "UnixTime": 1590432602
    },
    {
      "Action": "complete",
      "Agent": "User",
      "UnixTime": 1590432609
    }
  ],
  "FORMAT-VERSION": 7,
  "IntroducesConflicts": false,
  "Scenario": {
    "Domains": [
      "hotel"
    ],
    "Happy": false,
    "MultiTask": false,
    "UserTask": "Search for Hilton Hotel near the North part of town and note its rating. Follow the instructions on the left for now.",
    "WizardCapabilities": [
      {
        "Domain": "hotel",
        "SchemaImage": "hotel_search.jpg",
        "Task": "hotel_search"
      }
    ],
    "WizardTask": "Help the user find a specific hotel."
  },
  "UserQuestionnaire": [
    {
      "Answer": false,
      "Question": "Did the assistant reserve your hotel?"
    },
    {
      "Answer": true,
      "Question": "Did the assistant stay calm and helpful throughout the dialogue?"
    }
  ],
  "WizardQuestionnaire": [
    {
      "Answer": true,
      "Question": "Did the user change his/her mind about what he/she wants at any time?"
    },
    {
      "Answer": false,
      "Question": "Did the user become aggressive or annoyed during the dialogue? (Note: some users may be instructed to be annoying.)"
    },
    {
      "Answer": false,
      "Question": "Where you unsure about what to do at any time? (Feel free to send us an email with details.)"
    }
  ]
}